Metadata-Version: 2.1
Name: figurl-tiled-image
Version: 0.2.1
Summary: View a stack of tiled images via deck.gl
Home-page: https://github.com/scratchrealm/figurl-tiled-image
Author: Jeremy Magland
Author-email: jmagland@flatironinstitute.org
License: UNKNOWN
Project-URL: Bug Tracker, https://github.com/scratchrealm/figurl-tiled-image/issues
Platform: UNKNOWN
Classifier: Programming Language :: Python :: 3
Classifier: License :: OSI Approved :: Apache Software License
Classifier: Operating System :: OS Independent
License-File: LICENSE
